rlgraph_plot
