Metadata-Version: 1.0
Name: rlgraph-plot
Version: 0.0.2
Summary: RLgraph metagraph plotting library
Home-page: https://rlgraph.org
Author: RLgraph
Author-email: dev@rlgraph.org
License: Apache 2.0
Platform: UNKNOWN
